{
  "posts": [
    {
      "id": 1,
      "title": "Первый пост",
      "body": "О том как добавлять комменты в tsx",
      "created": 1675279518707,
      "userId": 1,
      "postId": 1
    },
    {
      "title": "Второй пост",
      "body": "Новый",
      "created": 1675330968318,
      "userId": 1,
      "id": 2,
      "postId": 1
    }
  ],
  "comments": [
    {
      "id": "1",
      "body": "Супер",
      "created": 1675279518707,
      "userId": "2",
      "postId": 1
    },
    {
      "id": "3",
      "body": "Отлично",
      "created": 1675279518708,
      "userId": "4",
      "postId": 1
    },
    {
      "id": "4",
      "body": "Ужас",
      "created": 1675279518709,
      "userId": "3",
      "postId": 1
    },
    {
      "id": "5",
      "body": "Автор - съешь говна",
      "created": 1675279518725,
      "userId": "3",
      "postId": 1
    }
  ]
}